universal_parser_it_stud_io/UniversalParser.py
"universal_parser_it_stud_io/__init__,py"
universal_parser_it_stud_io/ParserEngines/CsvParserEngine.py
universal_parser_it_stud_io/ParserEngines/JsonParserEngine.py
universal_parser_it_stud_io/ParserEngines/XmlParserEngine.py
universal_parser_it_stud_io/ParserEngines/YamlParserEngine.py
universal_parser_it_stud_io-1.0.1.dist-info/METADATA
universal_parser_it_stud_io-1.0.1.dist-info/WHEEL
universal_parser_it_stud_io-1.0.1.dist-info/licenses/LICENSE
universal_parser_it_stud_io-1.0.1.dist-info/RECORD
