Metadata-Version: 2.4
Name: universal_parser_it_stud_io
Version: 1.0.1
Summary: An universal parser for various file formats
Project-URL: Homepage, https://github.com/it-stud-io/universal-parser
Project-URL: Issues, https://github.com/it-stud-io/universal-parser/issues
Author-email: Christian Mueller <christian.mueller@it-stud.io>
License-File: LICENSE
Classifier: License :: OSI Approved :: MIT License
Classifier: Operating System :: OS Independent
Classifier: Programming Language :: Python :: 3
Requires-Python: >=3.8
Requires-Dist: jsonschema>=4.23.0
Requires-Dist: pyyaml>=6.0.2
Requires-Dist: xmlschema>=3.4.3
